postgres_client/__init__.py
postgres_client/core.py
postgres_client/utils.py
wf_postgres_client-0.1.2.dist-info/LICENSE
wf_postgres_client-0.1.2.dist-info/WHEEL
wf_postgres_client-0.1.2.dist-info/METADATA
wf_postgres_client-0.1.2.dist-info/RECORD
